LICENSE.txt
README.md
setup.py
bnapy/__init__.py
bnapy/cli.py
bnapy.egg-info/PKG-INFO
bnapy.egg-info/SOURCES.txt
bnapy.egg-info/dependency_links.txt
bnapy.egg-info/requires.txt
bnapy.egg-info/top_level.txt
bnapy/data/__init__.py
bnapy/dyad/__init__.py
bnapy/dyad/significant_edges.py
bnapy/dyad/tests/__init__.py
bnapy/individual/__init__.py
bnapy/individual/quantity_diversity.py
bnapy/individual/tests/__init__.py
bnapy/mesoscale/__init__.py
bnapy/mesoscale/clustering.py
bnapy/mesoscale/tests/__init__.py
bnapy/utils/__init__.py
bnapy/utils/graph_tools.py
bnapy/utils/tests/__init__.py
bnapy/visualization/__init__.py
bnapy/visualization/network_visualization.py
bnapy/visualization/tests/__init__.py