Metadata-Version: 2.2
Name: bnapy
Version: 0.6
Summary: Bipartite Network Analysis
Home-page: https://bnapy.readthedocs.io/en/latest/index.html
Author: Shihui Feng, Baiyue He, Alec Kirkley
Author-email: shihuife@hku.hk, baiyue.he@connect.hku.hk, akirkley@hku.hk
License: The MIT License
Project-URL: Documentation, https://bnapy.readthedocs.io/en/latest/index.html
Project-URL: Source, https://bnapy.readthedocs.io/en/latest/index.html
Requires-Python: >=3.9, <3.12
License-File: LICENSE.txt
Requires-Dist: numpy>=1.24
Requires-Dist: pandas>=2.2
Requires-Dist: scipy>=1.10
Requires-Dist: scikit-network==0.32.1
Dynamic: author
Dynamic: author-email
Dynamic: description
Dynamic: description-content-type
Dynamic: home-page
Dynamic: license
Dynamic: project-url
Dynamic: requires-dist
Dynamic: requires-python
Dynamic: summary
